badurls/__init__.py
badurls/url.py
badurls-0.12.dist-info/METADATA
badurls-0.12.dist-info/WHEEL
badurls-0.12.dist-info/entry_points.txt
badurls-0.12.dist-info/top_level.txt
badurls-0.12.dist-info/RECORD
