Metadata-Version: 2.4
Name: badurls
Version: 0.12
Summary: Simple URL obfuscation tool
Home-page: https://github.com/Anish-M-code/URL-obfuscator
Author: Anish M
Author-email: aneesh25861@gmail.com
License: GPLv3
Keywords: social engineering,cybersecurity,student project
Classifier: Topic :: Security
Classifier: Development Status :: 5 - Production/Stable
Classifier: Intended Audience :: Developers
Classifier: Operating System :: OS Independent
Classifier: License :: OSI Approved :: GNU General Public License v3 (GPLv3)
Classifier: Programming Language :: Python :: 3
Classifier: Intended Audience :: Developers
Classifier: Intended Audience :: Education
Dynamic: author
Dynamic: author-email
Dynamic: classifier
Dynamic: description
Dynamic: description-content-type
Dynamic: home-page
Dynamic: keywords
Dynamic: license
Dynamic: summary
